dbt_column_lineage/artifacts/adapter_mapping.py
dbt_column_lineage/artifacts/catalog.py
dbt_column_lineage/artifacts/exceptions.py
dbt_column_lineage/artifacts/manifest.py
dbt_column_lineage/artifacts/registry.py
dbt_column_lineage/artifacts/sql_parser.py
dbt_column_lineage/cli/main.py
dbt_column_lineage/lineage/display/__init__.py
dbt_column_lineage/lineage/display/base.py
dbt_column_lineage/lineage/display/dot.py
dbt_column_lineage/lineage/display/html/__init__.py
dbt_column_lineage/lineage/display/html/explore.py
dbt_column_lineage/lineage/display/html/static/css/styles.css
dbt_column_lineage/lineage/display/html/static/js/config.js
dbt_column_lineage/lineage/display/html/static/js/dataProcessor.js
dbt_column_lineage/lineage/display/html/static/js/exploration.js
dbt_column_lineage/lineage/display/html/static/js/graph.js
dbt_column_lineage/lineage/display/html/static/js/interactions.js
dbt_column_lineage/lineage/display/html/static/js/renderer.js
dbt_column_lineage/lineage/display/html/static/js/utils.js
dbt_column_lineage/lineage/display/html/static/vendor/d3.v7.min.js
dbt_column_lineage/lineage/display/html/templates/graph.html
dbt_column_lineage/lineage/display/text.py
dbt_column_lineage/lineage/service.py
dbt_column_lineage/models/__init__.py
dbt_column_lineage/models/schema.py
dbt_col_lineage-0.5.0.dist-info/METADATA
dbt_col_lineage-0.5.0.dist-info/WHEEL
dbt_col_lineage-0.5.0.dist-info/entry_points.txt
dbt_col_lineage-0.5.0.dist-info/licenses/LICENSE
dbt_col_lineage-0.5.0.dist-info/RECORD
